{"name": "", "screen_size": [800, 1000], "bottom_border_args": [[10, 980], [790, 980]], "objects": ["Goal", "Ball", "Container", "PlinkoBorder", "BottomBorder"], "plinko_border_args": [992, 800], "ball_args": [{"position": [374.9003278109933, 57.56049291239158]}], "goal_args": [{"position": [360.0, 351.2251360856309]}], "container_args": [{"position": [500, 700], "width": 80, "length": 10, "angle": -30}, {"position": [150, 710], "width": 50, "length": 10, "angle": 70}, {"position": [700, 200], "width": 44, "length": 10, "angle": 34}, {"position": [100, 500], "width": 47, "length": 10, "angle": -70}]}